rnaseeker/__init__.py
rnaseeker/main.py
rnaseeker/version.py
rnaseeker/fasta/__init__.py
rnaseeker/fasta/extract_promoters.py
rnaseeker/fasta/fasta_filter.py
rnaseeker/fasta/fasta_split.py
rnaseeker/gene_ontology/__init__.py
rnaseeker/gene_ontology/go_filter.py
rnaseeker/sequence/__init__.py
rnaseeker/sequence/sequence_io.py
rnaseeker-1.0.0.dist-info/LICENSE
rnaseeker-1.0.0.dist-info/METADATA
rnaseeker-1.0.0.dist-info/WHEEL
rnaseeker-1.0.0.dist-info/entry_points.txt
rnaseeker-1.0.0.dist-info/top_level.txt
rnaseeker-1.0.0.dist-info/RECORD
