Metadata-Version: 2.1
Name: rnaseeker
Version: 1.0.0
Summary: RNA-seq scripts and libraries
Home-page: https://github.com/jtompkin/rnaseeker
Author: Josh Tompkin
Author-email: jtompkindev@gmail.com
License: MIT
Keywords: rna,rnaseq,dna,fasta,fastq,bio,gene
Classifier: Programming Language :: Python :: 3
Classifier: License :: OSI Approved :: MIT License
Requires-Python: >=3.7
License-File: LICENSE
